{
  "enabled": true,
  "neededInstalledMods": [],
  "spawns": [
    {
      "id": "245-suicune",
      "pokemon": "suicune",
      "presets": ["natural","wild"],
      "type": "pokemon",
      "context": "surface",
      "bucket": "ultra-rare",
      "level": "50-60",
      "weight": 5.1,
      "condition": {
        "biomes": [
          "twilightforest:lake",
          "eternal_starlight:starlit_sea"
        ],
        "season": "autumn",
        "weather": "rain",
        "key_item": "mythsandlegends:clear_bell"
      }
    }
  ]
}